[
  {
    "img" : "https://this-person-does-not-exist.com/img/avatar-0eb5552ecf601f3c250fd49a05530654.jpg",
    "name" : "John",
    "position" : "Chief Engineer",
    "_id": "62bd5fba34a8f1c90303055c",
    "index": 0,
    "email": "mcdonaldholden@xerex.com",
    "nameList": [
      {
        "id": 0,
        "name": "Wendi Mooney"
      },
      {
        "id": 2,
        "name": "Holloway Whitehead"
      }
    ]
  },
  {
"img" : "https://this-person-does-not-exist.com/img/avatar-0eb5552ecf601f3c250fd49a05530654.jpg",   
    "position" : "Chief Engineer",
    "_id": "62bd5fbac3e5a4fca5e85e81",
    "index": 1,
    "nameList": [
      {
        "id": 0,
        "name": "Janine Barrett"
      },
      {
        "id": 1,
        "name": "Odonnell Savage"
      },
      {
        "id": 2,
        "name": "Patty Owen"
      }
    ]
  },
  {
    "img" : "https://this-person-does-not-exist.com/img/avatar-0eb5552ecf601f3c250fd49a05530654.jpg",
    "name" : "Mike",
    "_id": "62bd5fbaf8f417d849c135db",
    "position" : "Chief Engineer",
    "index": 2,
    "email": "pattyowen@xerex.com",
    "nameList": [
      {
        "id": 0,
        "name": "Earline Goff"
      },
      {
        "id": 1,
        "name": "Glenna Lawrence"
      },
      {
        "id": 7,
        "name": "Bettye Sawyer"
      }
    ]
  },
  {
    "img" : "https://this-person-does-not-exist.com/img/avatar-0eb5552ecf601f3c250fd49a05530654.jpg",
    "name" : "Andy",
    "index": 3,
    "position" : "Chief Engineer",
    "email": "bettyesawyer@xerex.com",
    "nameList": [
      {
        "id": 0,
        "name": "Judy Tate"
      },
      {
        "id": 1,
        "name": "Kaufman Garner"
      },
      {
        "id": 2,
        "name": "Reeves Armstrong"
      }
    ]
  },
  {
    "img" : "https://this-person-does-not-exist.com/img/avatar-0eb5552ecf601f3c250fd49a05530654.jpg",
    "name" : "Phil",
    "_id": "62bd5fbaada5da5b0a12b61b",
    "position" : "Chief Engineer",
    "index": 4,
    "email": "reevesarmstrong@xerex.com",
    "nameList": [
      {
        "id": 0,
        "name": "Reyes Garrison"
      },
      {
        "id": 1,
        "name": "Oneil Potts"
      },
      {
        "id": 2,
        "name": "Jean Conway"
      },
         {
        "id": "3",
        "name": "Jean Conway"
      }
    ]
  },
  {
    "img" : "https://this-person-does-not-exist.com/img/avatar-0eb5552ecf601f3c250fd49a05530654.jpg",
    "name" : "Statham",
    "_id": "62bd5fbaf8db7adc7f5b19ed",
    "position" : "Chief Engineer",
    "index": 5,
    "email": "jeanconway@xerex.com",
    "nameList": [
      {
        "id": 0
      },
      {
        "name": "Lacey Noel"
      },
      {
        "id": 2,
        "name": "Medina Suarez"
      }
    ]
  },
  {
     "img" : "https://this-person-does-not-exist.com/img/avatar-0eb5552ecf601f3c250fd49a05530654.jpg",
    "name" : "James",
    "position" : "Chief Engineer",
    "index": 6,
    "nameList": [
      {
        "id": 1,
        "name": "Brittany Maynard"
      },
      {
        "id": 1,
        "name": "Silva Harvey"
      },
      {
        "id": 2,
        "name": "Wolf Davis"
      }
    ]
  }
]